Metadata-Version: 2.1
Name: odoo-addon-purchase_order_line_sequence
Version: 18.0.1.0.0.10
Requires-Python: >=3.10
Requires-Dist: odoo-addon-stock_picking_line_sequence==18.0.*
Requires-Dist: odoo==18.0.*
Summary: Adds sequence to PO lines and propagates it toInvoice lines and Stock Moves
Home-page: https://github.com/OCA/purchase-workflow
License: AGPL-3
Author: Camptocamp, ForgeFlow, Serpent CS, Odoo Community Association (OCA)
Author-email: support@odoo-community.org
Classifier: Programming Language :: Python
Classifier: Framework :: Odoo
Classifier: Framework :: Odoo :: 18.0
Classifier: License :: OSI Approved :: GNU Affero General Public License v3
